log/__init__.py
log_KHARNEIT-0.0.1.dist-info/LICENSE.txt
log_KHARNEIT-0.0.1.dist-info/METADATA
log_KHARNEIT-0.0.1.dist-info/WHEEL
log_KHARNEIT-0.0.1.dist-info/top_level.txt
log_KHARNEIT-0.0.1.dist-info/RECORD
